lnl_surrogate/__init__.py
lnl_surrogate/_version.py
lnl_surrogate/cli.py
lnl_surrogate/logger.py
lnl_surrogate/kl_distance/__init__.py
lnl_surrogate/kl_distance/batch_distance_computer.py
lnl_surrogate/kl_distance/kl_distance.py
lnl_surrogate/plotting/__init__.py
lnl_surrogate/plotting/diagnostics.py
lnl_surrogate/plotting/plot_median_model.py
lnl_surrogate/surrogate/__init__.py
lnl_surrogate/surrogate/lnl_surrogate.py
lnl_surrogate/surrogate/model.py
lnl_surrogate/surrogate/sample.py
lnl_surrogate/surrogate/train.py
lnl_surrogate/surrogate/utils.py
lnl_surrogate/surrogate/managers/__init__.py
lnl_surrogate/surrogate/managers/data_manager.py
lnl_surrogate/surrogate/managers/optimiser_manager.py
compas_surrogate.lnl_surrogate-0.1.1.dist-info/METADATA
compas_surrogate.lnl_surrogate-0.1.1.dist-info/WHEEL
compas_surrogate.lnl_surrogate-0.1.1.dist-info/entry_points.txt
compas_surrogate.lnl_surrogate-0.1.1.dist-info/top_level.txt
compas_surrogate.lnl_surrogate-0.1.1.dist-info/RECORD
