Metadata-Version: 2.1
Name: compas_surrogate.lnl_surrogate
Version: 0.1.1
Summary: Build a surrogate for your LnL(d|θ)± ΔLnL(d|θ)
Author-email: Avi Vajpeyi <avi.vajpeyi@gmail.com>
Project-URL: Homepage, https://github.com/COMPAS-Surrogate/lnl_surrogate
Project-URL: Bug Reports, https://github.com/COMPAS-Surrogate/lnl_surrogate/issues
Project-URL: Source, https://github.com/COMPAS-Surrogate/lnl_surrogate/
Classifier: Development Status :: 3 - Alpha
Classifier: Intended Audience :: Science/Research
Classifier: License :: OSI Approved :: MIT License
Classifier: Operating System :: OS Independent
Classifier: Programming Language :: Python :: 3.8
Requires-Python: >=3.8
Requires-Dist: trieste[plotting]
Requires-Dist: scikit-optimize
Requires-Dist: gpflow
Requires-Dist: tensorflow
Requires-Dist: pandas
Requires-Dist: corner
Requires-Dist: tqdm
Requires-Dist: compas_surrogate.lnl_computer
Requires-Dist: compas_surrogate.ogc4_interface
Requires-Dist: compas_surrogate.acquisition_plotting
Provides-Extra: dev
Requires-Dist: pytest>=6.0; extra == "dev"
Requires-Dist: pytest-cov>=4.1.0; extra == "dev"
Requires-Dist: coverage[toml]; extra == "dev"
Requires-Dist: pre-commit; extra == "dev"
Requires-Dist: flake8>=5.0.4; extra == "dev"
Requires-Dist: black==22.10.0; extra == "dev"
Requires-Dist: jupyter-book; extra == "dev"
